Metadata-Version: 2.1
Name: simplace
Version: 5.0.2
Summary: Interact with the simulation framework Simplace
Home-page: https://www.simplace.net/
Author: Gunther Krauss
Author-email: guntherkrauss@uni-bonn.de
License: GPL3
Platform: UNKNOWN
Classifier: Development Status :: 4 - Beta
Classifier: Intended Audience :: Developers
Classifier: Intended Audience :: Science/Research
Classifier: Topic :: Scientific/Engineering
Classifier: Programming Language :: Python
Classifier: Programming Language :: Java
License-File: LICENSE
